odoo8_addon_product_variant_inactive-8.0.0.0.0-py2.7-nspkg.pth
odoo_addons/product_variant_inactive/__openerp__.py
odoo_addons/product_variant_inactive/product_variant.py
odoo_addons/product_variant_inactive/product_variant_view.xml
odoo_addons/product_variant_inactive/__init__.py
odoo_addons/product_variant_inactive/README.rst
odoo_addons/product_variant_inactive/product.product.csv
odoo_addons/product_variant_inactive/static/description/icon.png
odoo_addons/product_variant_inactive/static/description/unactive.png
odoo8_addon_product_variant_inactive-8.0.0.0.0.dist-info/top_level.txt
odoo8_addon_product_variant_inactive-8.0.0.0.0.dist-info/WHEEL
odoo8_addon_product_variant_inactive-8.0.0.0.0.dist-info/RECORD
odoo8_addon_product_variant_inactive-8.0.0.0.0.dist-info/metadata.json
odoo8_addon_product_variant_inactive-8.0.0.0.0.dist-info/DESCRIPTION.rst
odoo8_addon_product_variant_inactive-8.0.0.0.0.dist-info/METADATA
odoo8_addon_product_variant_inactive-8.0.0.0.0.dist-info/namespace_packages.txt
